drf_dog/__init__.py
drf_dog/serializers.py
drf_dog/__pycache__/__init__.cpython-38.pyc
drf_dog/__pycache__/serializers.cpython-38.pyc
drf_dog-0.1.0.dist-info/LICENSE
drf_dog-0.1.0.dist-info/METADATA
drf_dog-0.1.0.dist-info/WHEEL
drf_dog-0.1.0.dist-info/top_level.txt
drf_dog-0.1.0.dist-info/RECORD
